km2testcase/__init__.py
km2testcase/cli.py
km2testcase/model.py
km2testcase/parser.py
km2testcase/writter.py
km2testcase/writter_mixin.py
km2testcase-0.1.5.dist-info/METADATA
km2testcase-0.1.5.dist-info/WHEEL
km2testcase-0.1.5.dist-info/entry_points.txt
km2testcase-0.1.5.dist-info/licenses/LICENSE
km2testcase-0.1.5.dist-info/RECORD
