Metadata-Version: 2.1
Name: km2testcase
Version: 0.1.5
Summary: km to testcase! 
Project-URL: Source, https://github.com/wh1isper/km2testcase
Author-email: Wh1isper <9573586@qq.com>
License: BSD 3-Clause License
License-File: LICENSE
Keywords: km2testcase,testcase,zentao
Classifier: License :: OSI Approved :: BSD License
Classifier: Operating System :: OS Independent
Classifier: Programming Language :: Python :: 3
Requires-Python: >=3.7
Requires-Dist: click
Requires-Dist: pydantic<2
Provides-Extra: test
Requires-Dist: pytest; extra == 'test'
